algocomp/__init__.py
algocomp/master.py
algocomp-1.0.5.dist-info/LICENSE
algocomp-1.0.5.dist-info/METADATA
algocomp-1.0.5.dist-info/WHEEL
algocomp-1.0.5.dist-info/top_level.txt
algocomp-1.0.5.dist-info/RECORD
